promptdefend/__init__.py
promptdefend-1.0.0.dist-info/licenses/LICENSE
promptdefend-1.0.0.dist-info/METADATA
promptdefend-1.0.0.dist-info/WHEEL
promptdefend-1.0.0.dist-info/top_level.txt
promptdefend-1.0.0.dist-info/RECORD
